fhadmin/__init__.py
fhadmin/_modidx.py
fhadmin/core.py
fhadmin-0.0.1.dist-info/licenses/LICENSE
fhadmin-0.0.1.dist-info/METADATA
fhadmin-0.0.1.dist-info/WHEEL
fhadmin-0.0.1.dist-info/entry_points.txt
fhadmin-0.0.1.dist-info/top_level.txt
fhadmin-0.0.1.dist-info/RECORD
